examples/fulladder/fulladd.v
module fulladd(
 input a,
 input b,
 input c,
 output  reg sum,
 output  reg carry
 );
 always@(a or b or c)
 begin
  sum <= a ^ b ^ c;
  carry <= (a&b) | (b&c) | (c&a);
  end
  endmodule

examples/fulladder/fulladd_tb.v
module fulladd_tb;
 	reg a;
 	reg b;
 	reg c;
 	wire sum;
	wire carry;
 
 fulladd u0(
 	.a(a),
 	.b(b),
 	.c(c),
 	.sum(sum),
 	.carry(carry)
 	);
 	
 initial begin
 $dumpfile("test_fulladd.vcd");
 $dumpvars(0,fulladd_tb);
  #10 a=0;b=0;c=0;
  #10 a=0;b=0;c=1;
  #10 a=0;b=1;c=0;
  #10 a=0;b=1;c=1;
  #10 a=1;b=0;c=0;
  #10 a=1;b=0;c=1;
  #10 a=1;b=1;c=0;
  #10 a=1;b=1;c=1;
  #100 $finish;
  end
  endmodule

examples/fulladder/test_fulladd.vcd
$date
	Thu Apr  4 16:11:17 2024
$end
$version
	Icarus Verilog
$end
$timescale
	1s
$end
$scope module fulladd_tb $end
$var wire 1 ! sum $end
$var wire 1 " carry $end
$var reg 1 # a $end
$var reg 1 $ b $end
$var reg 1 % c $end
$scope module u0 $end
$var wire 1 # a $end
$var wire 1 $ b $end
$var wire 1 % c $end
$var reg 1 " carry $end
$var reg 1 ! sum $end
$upscope $end
$upscope $end
$enddefinitions $end
#0
$dumpvars
x%
x$
x#
x"
x!
$end
#10
0"
0!
0%
0$
0#
#20
1!
1%
#30
0%
1$
#40
1"
0!
1%
#50
0"
1!
0%
0$
1#
#60
1"
0!
1%
#70
0%
1$
#80
1!
1%
