examples/fsm/fsm.v
module fsm(
  input clk,
  output reg [2:0] light,
  output reg [1:0] state
);

parameter s0 = 0, s1 = 1, s2 = 2;
parameter red = 3'b100, yellow = 3'b010, green = 3'b001;

reg [2:0] next_state;

always @(posedge clk) begin
    case (state)
        s0: next_state <= s1;
        s1: next_state <= s2;
        s2: next_state <= s0;
        default: next_state <= s0;
    endcase
end

always @(posedge clk) begin
    state <= next_state;
end

always @(*) begin
    case (state)
        s0: light = red;
        s1: light = yellow;
        s2: light = green;
        default: light = red;
    endcase
end

endmodule

examples/fsm/fsm_tb.v
module fsm_tb;

  reg clk = 0; // Clock signal
  reg rst = 0; // Reset signal
  wire [2:0] light; // Output signal (declare as wire)
  wire [1:0] state; // Output signal (declare as wire)

  // Instantiate FSM module
  fsm uut (
    .clk(clk),
    .light(light),
    .state(state)
  );

  // Clock generation
  always #5 clk = ~clk;

  // Reset generation
  initial begin
    #10 rst = 1; // Assert reset
    #20 rst = 0; // Deassert reset
  end

  // Monitor
  always @(posedge clk) begin
    $dumpfile("test_fsm.vcd");
    $dumpvars(0,fsm_tb);
  // End simulation after 100 time units
 
    #100 $finish;
  end

endmodule

examples/fsm/test_fsm.vcd
$date
	Wed Apr 10 12:37:22 2024
$end
$version
	Icarus Verilog
$end
$timescale
	1s
$end
$scope module fsm_tb $end
$var wire 2 ! state [1:0] $end
$var wire 3 " light [2:0] $end
$var reg 1 # clk $end
$var reg 1 $ rst $end
$scope module uut $end
$var wire 1 # clk $end
$var reg 3 % light [2:0] $end
$var reg 3 & next_state [2:0] $end
$var reg 2 ' state [1:0] $end
$upscope $end
$upscope $end
$enddefinitions $end
#5
$dumpvars
bx '
b0 &
bx %
0$
1#
bx "
bx !
$end
#10
0#
1$
#15
b100 "
b100 %
b0 !
b0 '
1#
#20
0#
#25
b1 &
1#
#30
0#
0$
#35
b10 "
b10 %
b1 !
b1 '
1#
#40
0#
#45
b10 &
1#
#50
0#
#55
b1 "
b1 %
b10 !
b10 '
1#
#60
0#
#65
b0 &
1#
#70
0#
#75
b100 "
b100 %
b0 !
b0 '
1#
#80
0#
#85
b1 &
1#
#90
0#
#95
b10 "
b10 %
b1 !
b1 '
1#
#100
0#
#105
b10 &
1#
