examples/jkff/jkff.v
module jkff (
    input clk,
    input  j,
    input  k,
    output reg q = 1'b0,
    output reg qn = 1'b1
);

always @(posedge clk) begin
    case ({j, k})
        2'b00: begin 
            q <= q;
            qn <= qn;
        end
        2'b01: begin 
            q <= 1'b0;
            qn <= 1'b1;
        end
        2'b10: begin 
            q <= 1'b1;
            qn <= 1'b0;
        end
        2'b11: begin 
            q <= ~q;
            qn <= ~qn;
        end
    endcase
end

endmodule

examples/jkff/jkff_tb.v
module jkff_tb;

reg clk;
reg j;
reg k;
wire q;
wire qn;

jkff u0 (
    .clk(clk),
    .j(j),
    .k(k),
    .q(q),
    .qn(qn)
);

initial begin
    $dumpfile("test_jkff.vcd");
    $dumpvars(0, jkff_tb);
    clk = 0;
    j = 0;
    k = 0;
    #10; // Initial stabilization time
    // Set initial values
    j = 1;
    k = 0;
    #10;
    j = 0;
    k = 1;
    #10;
    j = 1;
    k = 1;
    #100; // Simulation duration
    $finish;
end

always #5 clk = ~clk; // Clock toggle

endmodule

examples/jkff/test_jkff.vcd
$date
	Wed May 15 18:44:09 2024
$end
$version
	Icarus Verilog
$end
$timescale
	1s
$end
$scope module jkff_tb $end
$var wire 1 ! qn $end
$var wire 1 " q $end
$var reg 1 # clk $end
$var reg 1 $ j $end
$var reg 1 % k $end
$scope module u0 $end
$var wire 1 # clk $end
$var wire 1 $ j $end
$var wire 1 % k $end
$var reg 1 " q $end
$var reg 1 ! qn $end
$upscope $end
$upscope $end
$enddefinitions $end
#0
$dumpvars
0%
0$
0#
0"
1!
$end
#5
1#
#10
0#
1$
#15
0!
1"
1#
#20
0#
1%
0$
#25
1!
0"
1#
#30
0#
1$
#35
0!
1"
1#
#40
0#
#45
1!
0"
1#
#50
0#
#55
0!
1"
1#
#60
0#
#65
1!
0"
1#
#70
0#
#75
0!
1"
1#
#80
0#
#85
1!
0"
1#
#90
0#
#95
0!
1"
1#
#100
0#
#105
1!
0"
1#
#110
0#
#115
0!
1"
1#
#120
0#
#125
1!
0"
1#
